tecio/__init__.py
tecio/tecio.py
tecio-2.0.6.dist-info/licenses/LICENSE.txt
tecio-2.0.6.dist-info/METADATA
tecio-2.0.6.dist-info/WHEEL
tecio-2.0.6.dist-info/top_level.txt
tecio-2.0.6.dist-info/RECORD
