Metadata-Version: 2.4
Name: tecio
Version: 2.0.6
Summary: A pure python package to read and write Tecplot binary data
Author-email: Han Luo <6806720+luohancfd@users.noreply.github.com>
License:                     GNU GENERAL PUBLIC LICENSE
Project-URL: Homepage, https://github.com/luohancfd/tecio
Project-URL: Bug Tracker, https://github.com/luohancfd/tecio/issues
Classifier: Operating System :: OS Independent
Classifier: Programming Language :: Python :: 3.9
Classifier: Programming Language :: Python :: 3.10
Classifier: Programming Language :: Python :: 3.11
Classifier: Programming Language :: Python :: 3.12
Classifier: License :: OSI Approved :: GNU General Public License v3 or later (GPLv3+)
Classifier: Topic :: Scientific/Engineering
Requires-Python: >=3.9
License-File: LICENSE.txt
Requires-Dist: construct>=2.10.67
Requires-Dist: numpy
Dynamic: license-file
